gaft/__init__.py
gaft/engine.py
gaft/mpiutil.py
gaft/analysis/__init__.py
gaft/analysis/console_output.py
gaft/analysis/fitness_store.py
gaft/components/__init__.py
gaft/components/binary_individual.py
gaft/components/decimal_individual.py
gaft/components/individual.py
gaft/components/population.py
gaft/operators/__init__.py
gaft/operators/crossover/__init__.py
gaft/operators/crossover/uniform_crossover.py
gaft/operators/mutation/__init__.py
gaft/operators/mutation/flip_bit_mutation.py
gaft/operators/selection/__init__.py
gaft/operators/selection/exponential_ranking_selection.py
gaft/operators/selection/linear_ranking_selection.py
gaft/operators/selection/roulette_wheel_selection.py
gaft/operators/selection/tournament_selection.py
gaft/plugin_interfaces/__init__.py
gaft/plugin_interfaces/analysis.py
gaft/plugin_interfaces/metaclasses.py
gaft/plugin_interfaces/operators/__init__.py
gaft/plugin_interfaces/operators/crossover.py
gaft/plugin_interfaces/operators/mutation.py
gaft/plugin_interfaces/operators/selection.py
gaft/tests/__init__.py
gaft/tests/dynamic_linear_scaling_test.py
gaft/tests/engine_test.py
gaft/tests/exponential_ranking_selection_test.py
gaft/tests/flip_bit_big_mutation_test.py
gaft/tests/flip_bit_mutation_test.py
gaft/tests/individual_test.py
gaft/tests/linear_ranking_selection_test.py
gaft/tests/linear_scaling_test.py
gaft/tests/mpiutil_test.py
gaft/tests/population_test.py
gaft/tests/roulette_wheel_selection_test.py
gaft/tests/test_all.py
gaft/tests/tournament_selection_test.py
gaft/tests/uniform_crossover_test.py
gaft-0.5.7.dist-info/DESCRIPTION.rst
gaft-0.5.7.dist-info/METADATA
gaft-0.5.7.dist-info/RECORD
gaft-0.5.7.dist-info/WHEEL
gaft-0.5.7.dist-info/metadata.json
gaft-0.5.7.dist-info/top_level.txt
