Metadata-Version: 2.0
Name: gaft
Version: 0.5.7
Summary: A Genetic Algorithm Framework in Python
Home-page: https://github.com/PytLab/gaft
Author: Shao-Zheng-Jiang
Author-email: shaozhengjiang@gmail.com
License: LICENSE
Download-URL: https://github.com/PytLab/gaft/releases
Platform: linux
Platform: windows
Platform: macos
